setup.py
distromath/Binomialdistribution.py
distromath/Gaussiandistribution.py
distromath/Generaldistribution.py
distromath/__init__.py
distromath.egg-info/PKG-INFO
distromath.egg-info/SOURCES.txt
distromath.egg-info/dependency_links.txt
distromath.egg-info/not-zip-safe
distromath.egg-info/top_level.txt