Metadata-Version: 1.0
Name: distromath
Version: 1.0
Summary: Gaussian and Binomial distributions
Home-page: UNKNOWN
Author: Nathaniel Solomon
Author-email: nathaniel.o.solomon@gmail.com
License: UNKNOWN
Platform: UNKNOWN
